README.rst
setup.cfg
setup.py
src/mpfhandler.py
src/mpfhandler.egg-info/PKG-INFO
src/mpfhandler.egg-info/SOURCES.txt
src/mpfhandler.egg-info/dependency_links.txt
src/mpfhandler.egg-info/requires.txt
src/mpfhandler.egg-info/top_level.txt