Metadata-Version: 1.1
Name: mpfhandler
Version: 0.0.1
Summary: a timed rotate logging file handler, support multiple processes (base logging.RotatingFileHandler, portalocker)
Home-page: https://github.com/yorks/mpfhandler
Author: yorks
Author-email: stuyorks@gmail.com
License: http://www.apache.org/licenses/LICENSE-2.0
Download-URL: https://github.com/yorks/mpfhandler/releases/tag/0.0.1
Keywords: logging,linux,unix,rotate,portalocker,django,mutiple processes
Platform: nt
Platform: posix
Classifier: Development Status :: 4 - Beta
Classifier: Topic :: System :: Logging
Classifier: Operating System :: POSIX
Classifier: Programming Language :: Python
Classifier: Programming Language :: Python :: 2.6
Classifier: Programming Language :: Python :: 2.7
Classifier: Topic :: Software Development :: Libraries :: Python Modules
Classifier: License :: OSI Approved :: Apache Software License
